{
   "markers" : [
      {
         "pin" : "not",
         "text" : "01 Taranis\nHyades Sector FB-N b7-6",
         "x" : 88.4375,
         "y" : -74.90625,
         "z" : -122
      },
	  {
		 "pin" : "not",
         "text" : "02 Leigong\nHIP 8887",
         "x" : -66.4375,
         "y" : -144.40625,
         "z" : -106.28125
      },
	  {
         "pin" : "not",
         "text" : "03 Indra\nHIP 20567",
         "x" : -2.8125,
         "y" : -63.8125,
         "z" : -162.4375
      },
	  {
         "pin" : "not",
         "text" : "04 Oya\nCephei Sector BV-Y b4",
         "x" : -97.8125,
         "y" : 44.3125,
         "z" : -83.84375
      },
	  {
         "pin" : "not",
         "text" : "05 Cocijo\nCol 285 Sector BA-P c6-18",
         "x" : 157.28125,
         "y" : 14.96875,
         "z" : -103.875
      },
	  {
         "pin" : "carriergreen",
         "text" : "PDES Cloudbase\nPhill P\nCuchan\nMain Star",
         "x" : 95.375,
         "y" : -72.59375,
         "z" : -84.125
      },
	  	  {
         "pin" : "carriergreen",
         "text" : "[32 SC]The Adamant Crow (J6J-09B)\nJackHarkness85\nCuchan\nMain Star",
         "x" : 95.375,
         "y" : -72.59375,
         "z" : -84.125
      },
	  	  {
         "pin" : "carriergreen",
         "text" : "Puzzles Bar & Grill (K7F-N1Y)\nHalpy\nTrianguli Sector EQ-Y b5",
         "x" : 95.375,
         "y" : -72.59375,
         "z" : -84.125
      },
	  	  {
         "pin" : "carriergreen",
         "text" : "TSCS Golden Age (H7K-G1J)\nBaknar (Terran Survey Corps)\nHyades Sector GW-W d1-88",
         "x" : 95.375,
         "y" : -72.59375,
         "z" : -84.125
      },
	  	  {
         "pin" : "carriergreen",
         "text" : "PDES Nameless\nAzureAssaulter\nPhrygiang",
         "x" : 95.375,
         "y" : -72.59375,
         "z" : -84.125
      },
	  {
         "pin" : "orbis",
         "text" : "Rescue Priority\nHIP 23716\nWakata Station",
         "x" : -66.4375,
         "y" : -144.40625,
         "z" : -106.28125
      }
  ]
}